{
  "is_active": true,
  "version": "1.0.0",
  "message": "Chào mừng bạn đến với 2TStudio. Hiện tại auto đang bảo trì, vui lòng liên hệ với admin để biết thêm chi tiết",
  "licensed_machines": {
    "006vffWXH3TJ60ZZdRECJNMN": "",
    "005iBZ7VXWrHEjH1xRiGJNg2": "",
    "003NqbzWNMKFvXDtCn52FEvz": "2026-5-23"
  },
  "ptr_map": ["0x29AAC04"],
  "ptr_x": ["0x4C3538"],
  "ptr_y": ["0x4C353C"],
  "ptr_tdd_stt": ["0x4A47A8"],
  "ptr_ttd_stt": ["0x49F0E4"],
  "ui_input_x": {
    "base": "0x2B01DC",
    "offsets": ["0x84"]
  },
  "ui_input_y": {
    "base": "0x2B2C88",
    "offsets": ["0x230"]
  },
  "ui_select_diem_den_map": {
    "base": "0x2B10FC",
    "offsets": ["0x230","0x3C","0x38","0x38","0x38","0x44","0x3C","0xF5C"]
  },
  "ui_select_move": {
    "base": "0x2B01E8",
    "offsets": ["0x2F4"]
  },
  "offset_ten_nv": "0x2B36D0"
}
